py_m3u/__init__.py
py_m3u/_m3u.py
py_m3u/_type_aliases.py
py_m3u/_version.py
py_m3u/directives.py
py_m3u-0.0.1.dist-info/LICENSE.md
py_m3u-0.0.1.dist-info/METADATA
py_m3u-0.0.1.dist-info/WHEEL
py_m3u-0.0.1.dist-info/top_level.txt
py_m3u-0.0.1.dist-info/RECORD
