Metadata-Version: 2.1
Name: py_m3u
Version: 0.0.1
Summary: A simple and flexible m3u parser in python with no third-party requirements
Home-page: https://github.com/Eastern-Skill7173/py_m3u
Author: Eastern-Skill7173
Requires-Python: >=3.8
License-File: LICENSE.md
